uipath/robot/__init__.py
uipath/robot/py.typed
uipath/robot/infra/__init__.py
uipath/robot/infra/logger.py
uipath/robot/models/__init__.py
uipath/robot/models/heartbeat.py
uipath/robot/services/__init__.py
uipath/robot/services/identity.py
uipath/robot/services/orchestrator.py
uipath_robot-0.0.3.dist-info/METADATA
uipath_robot-0.0.3.dist-info/WHEEL
uipath_robot-0.0.3.dist-info/entry_points.txt
uipath_robot-0.0.3.dist-info/licenses/LICENSE
uipath_robot-0.0.3.dist-info/RECORD
