Metadata-Version: 2.4
Name: uipath-robot
Version: 0.0.3
Summary: UiPath Robot Simulator
Project-URL: Homepage, https://uipath.com
Project-URL: Documentation, https://uipath.github.io/uipath-python/
Maintainer-email: Cristian Pufu <cristian.pufu@uipath.com>
License-File: LICENSE
Classifier: Intended Audience :: Developers
Classifier: Programming Language :: Python :: 3.11
Classifier: Programming Language :: Python :: 3.12
Classifier: Programming Language :: Python :: 3.13
Classifier: Topic :: Software Development :: Build Tools
Requires-Python: >=3.11
Requires-Dist: httpx>=0.28.1
Requires-Dist: pydantic<3.0.0,>=2.12.5
Requires-Dist: uipath>=2.4.0
